post_man/__init__.py
webapitest/__init__.py
webapitest/main.py
webapitest/postman.py
webapitest/project.py
webapitest/validator.py
webapitest/lib/__init__.py
webapitest/lib/_typing.py
webapitest/lib/base.py
webapitest/lib/case.py
webapitest/lib/scene.py
webapitest/lib/utils.py
webapitest-0.1.5.data/data/README.md
webapitest-0.1.5.dist-info/LICENSE
webapitest-0.1.5.dist-info/METADATA
webapitest-0.1.5.dist-info/WHEEL
webapitest-0.1.5.dist-info/entry_points.txt
webapitest-0.1.5.dist-info/top_level.txt
webapitest-0.1.5.dist-info/RECORD
