Metadata-Version: 2.1
Name: webapitest
Version: 0.1.5
Summary: Testing tool for web api
Home-page: https://gitee.com/wow_1/webapitest
Author: Huangyan
Author-email: 345471536@qq.com
License: MIT
Keywords: web,api,test,postman
Platform: UNKNOWN
Classifier: Programming Language :: Python :: 3.3
Classifier: Programming Language :: Python :: 3.4
Classifier: Programming Language :: Python :: 3.5
Classifier: Programming Language :: Python :: 3.6
Classifier: Programming Language :: Python :: 3.7
Classifier: Programming Language :: Python :: 3.8
Classifier: License :: OSI Approved :: Apache Software License
Classifier: Operating System :: OS Independent
Requires-Python: >=3.3
Requires-Dist: requests
